phion/__init__.py
phion/metadata.py
phion-0.0.1.dist-info/LICENSE
phion-0.0.1.dist-info/METADATA
phion-0.0.1.dist-info/WHEEL
phion-0.0.1.dist-info/top_level.txt
phion-0.0.1.dist-info/RECORD
