Metadata-Version: 2.1
Name: phion
Version: 0.0.1
Summary: Linux rice package manager core. The core library used by PHION cli and the gui application.
Home-page: https://github.com/phion-pm/core
Author: Aditya Gupta
Author-email: aditsuyag@gmail.com
License: UNKNOWN
Project-URL: Bug Tracker, https://github.com/phion-pm/core/issues
Platform: UNKNOWN
Classifier: Programming Language :: Python :: 3
Classifier: Programming Language :: Python :: 3.10
Classifier: Programming Language :: Python :: 3.9
Classifier: Programming Language :: Python :: 3.8
Classifier: License :: OSI Approved :: GNU General Public License v3 or later (GPLv3+)
Classifier: Operating System :: POSIX :: Linux
Classifier: Operating System :: MacOS :: MacOS X
Classifier: Development Status :: 1 - Planning
Classifier: Environment :: Console
Classifier: Intended Audience :: Developers
Classifier: Natural Language :: English
Classifier: Topic :: Desktop Environment :: Window Managers
License-File: LICENSE
Provides-Extra: dev
Requires-Dist: pytest (>=3.7) ; extra == 'dev'
